odoo/addons/crm_tag_multi_company_sale/README.rst
odoo/addons/crm_tag_multi_company_sale/__init__.py
odoo/addons/crm_tag_multi_company_sale/__manifest__.py
odoo/addons/crm_tag_multi_company_sale/i18n/crm_tag_multi_company_sale.pot
odoo/addons/crm_tag_multi_company_sale/i18n/it.po
odoo/addons/crm_tag_multi_company_sale/models/__init__.py
odoo/addons/crm_tag_multi_company_sale/models/sale_order.py
odoo/addons/crm_tag_multi_company_sale/readme/CONTRIBUTORS.rst
odoo/addons/crm_tag_multi_company_sale/readme/DESCRIPTION.rst
odoo/addons/crm_tag_multi_company_sale/static/description/icon.png
odoo/addons/crm_tag_multi_company_sale/static/description/index.html
odoo_addon_crm_tag_multi_company_sale-16.0.1.0.0.4.dist-info/METADATA
odoo_addon_crm_tag_multi_company_sale-16.0.1.0.0.4.dist-info/WHEEL
odoo_addon_crm_tag_multi_company_sale-16.0.1.0.0.4.dist-info/top_level.txt
odoo_addon_crm_tag_multi_company_sale-16.0.1.0.0.4.dist-info/RECORD
